gpt_explorer/__init__.py
gpt_explorer/__init__.pyc
gpt_explorer/compiler.py
gpt_explorer/explorer.py
gpt_explorer/explorer.pyc
gpt_explorer-0.2.0.dist-info/LICENSE
gpt_explorer-0.2.0.dist-info/METADATA
gpt_explorer-0.2.0.dist-info/WHEEL
gpt_explorer-0.2.0.dist-info/top_level.txt
gpt_explorer-0.2.0.dist-info/RECORD
